synth_data_gen/__init__.py
synth_data_gen/augmentation.py
synth_data_gen/config.py
synth_data_gen/privacy.py
synth_data_gen/tabular.py
synth_data_gen/text.py
synth_data_gen/timeseries.py
synth_data_gen/utils.py
synthflow-0.1.0.dist-info/licenses/LICENSE
synthflow-0.1.0.dist-info/METADATA
synthflow-0.1.0.dist-info/WHEEL
synthflow-0.1.0.dist-info/top_level.txt
synthflow-0.1.0.dist-info/RECORD
